LICENSE
MANIFEST.in
README.md
setup.py
django_nsa.egg-info/PKG-INFO
django_nsa.egg-info/SOURCES.txt
django_nsa.egg-info/dependency_links.txt
django_nsa.egg-info/not-zip-safe
django_nsa.egg-info/requires.txt
django_nsa.egg-info/top_level.txt
nsa/__init__.py
nsa/forms.py
nsa/models.py
nsa/urls.py
nsa/views.py
nsa/static/css/960.css
nsa/static/css/nsa.css
nsa/static/img/fuck_you.jpg
nsa/static/img/icon-no.gif
nsa/static/img/icon-yes.gif
nsa/static/img/nsa-eagle-tiny.png
nsa/templates/nsa/index.html
nsa/templates/nsa/layout.html
nsa/templates/nsa/logon.html
nsa/templates/nsa/users.html
nsa/templates/nsa/users_data.html
nsa/templates/nsa/warrant.html