Metadata-Version: 1.1
Name: django-nsa
Version: 0.1
Summary: An easy way for the NSA to see what's going on in our Django projects.
Home-page: https://github.com/lvm/django_nsa
Author: Mauro
Author-email: mauro@cacavoladora.org
License: MIT
Keywords: nsa,django,hype,yay,echelon
Platform: UNKNOWN
Classifier: Development Status :: 4 - Beta
Classifier: Environment :: Web Environment
Classifier: Intended Audience :: Developers
Classifier: Framework :: Django
Classifier: License :: OSI Approved :: MIT License
Classifier: Operating System :: OS Independent
Classifier: Programming Language :: Python
Classifier: Topic :: Communications
Classifier: Topic :: Internet
Classifier: Topic :: Security
